{"sentence_LOW": ["As", "I", "was", "saying", "yesterday", "in", "our", "meeting", ",", "I", "think", "we", "need", "to", "understand", "that", "the", "only", "possibility", "of", "successfully", "approaching", "globalization", "lies", "precisely", "in", "the", "setting", "of", "common", "rules", "which", "would", "be", "respected", "by", "all", "nations", ",", "developed", "and", "developing", "."], "sentence_words": [{"token": "As", "sentence_position": 0, "sentence_start": true, "sentence_end": false, "NEtag": "O"}, {"token": "I", "sentence_position": 1, "sentence_start": false, "sentence_end": false, "NEtag": "O"}, {"token": "was", "sentence_position": 2, "sentence_start": false, "sentence_end": false, "NEtag": "O"}, {"token": "saying", "sentence_position": 3, "sentence_start": false, "sentence_end": false, "NEtag": "O"}, {"token": "yesterday", "sentence_position": 4, "sentence_start": false, "sentence_end": false, "NEtag": "O"}, {"token": "in", "sentence_position": 5, "sentence_start": false, "sentence_end": false, "NEtag": "O"}, {"token": "our", "sentence_position": 6, "sentence_start": false, "sentence_end": false, "NEtag": "O"}, {"token": "meeting", "sentence_position": 7, "sentence_start": false, "sentence_end": false, "NEtag": "O"}, {"token": ",", "sentence_position": 8, "sentence_start": false, "sentence_end": false, "NEtag": "O"}, {"token": "I", "sentence_position": 9, "sentence_start": false, "sentence_end": false, "NEtag": "O"}, {"token": "think", "sentence_position": 10, "sentence_start": false, "sentence_end": false, "NEtag": "O"}, {"token": "we", "sentence_position": 11, "sentence_start": false, "sentence_end": false, "NEtag": "O"}, {"token": "need", "sentence_position": 12, "sentence_start": false, "sentence_end": false, "NEtag": "O"}, {"token": "to", "sentence_position": 13, "sentence_start": false, "sentence_end": false, "NEtag": "O"}, {"token": "understand", "sentence_position": 14, "sentence_start": false, "sentence_end": false, "NEtag": "O"}, {"token": "that", "sentence_position": 15, "sentence_start": false, "sentence_end": false, "NEtag": "O"}, {"token": "the", "sentence_position": 16, "sentence_start": false, "sentence_end": false, "NEtag": "O"}, {"token": "only", "sentence_position": 17, "sentence_start": false, "sentence_end": false, "NEtag": "O"}, {"token": "possibility", "sentence_position": 18, "sentence_start": false, "sentence_end": false, "NEtag": "O"}, {"token": "of", "sentence_position": 19, "sentence_start": false, "sentence_end": false, "NEtag": "O"}, {"token": "successfully", "sentence_position": 20, "sentence_start": false, "sentence_end": false, "NEtag": "O"}, {"token": "approaching", "sentence_position": 21, "sentence_start": false, "sentence_end": false, "NEtag": "O"}, {"token": "globalization", "sentence_position": 22, "sentence_start": false, "sentence_end": false, "NEtag": "O"}, {"token": "lies", "sentence_position": 23, "sentence_start": false, "sentence_end": false, "NEtag": "O"}, {"token": "precisely", "sentence_position": 24, "sentence_start": false, "sentence_end": false, "NEtag": "O"}, {"token": "in", "sentence_position": 25, "sentence_start": false, "sentence_end": false, "NEtag": "O"}, {"token": "the", "sentence_position": 26, "sentence_start": false, "sentence_end": false, "NEtag": "O"}, {"token": "setting", "sentence_position": 27, "sentence_start": false, "sentence_end": false, "NEtag": "O"}, {"token": "of", "sentence_position": 28, "sentence_start": false, "sentence_end": false, "NEtag": "O"}, {"token": "common", "sentence_position": 29, "sentence_start": false, "sentence_end": false, "NEtag": "O"}, {"token": "rules", "sentence_position": 30, "sentence_start": false, "sentence_end": false, "NEtag": "O"}, {"token": "which", "sentence_position": 31, "sentence_start": false, "sentence_end": false, "NEtag": "O"}, {"token": "would", "sentence_position": 32, "sentence_start": false, "sentence_end": false, "NEtag": "O"}, {"token": "be", "sentence_position": 33, "sentence_start": false, "sentence_end": false, "NEtag": "O"}, {"token": "respected", "sentence_position": 34, "sentence_start": false, "sentence_end": false, "NEtag": "O"}, {"token": "by", "sentence_position": 35, "sentence_start": false, "sentence_end": false, "NEtag": "O"}, {"token": "all", "sentence_position": 36, "sentence_start": false, "sentence_end": false, "NEtag": "O"}, {"token": "nations", "sentence_position": 37, "sentence_start": false, "sentence_end": false, "NEtag": "O"}, {"token": ",", "sentence_position": 38, "sentence_start": false, "sentence_end": false, "NEtag": "O"}, {"token": "developed", "sentence_position": 39, "sentence_start": false, "sentence_end": false, "NEtag": "O"}, {"token": "and", "sentence_position": 40, "sentence_start": false, "sentence_end": false, "NEtag": "O"}, {"token": "developing", "sentence_position": 41, "sentence_start": false, "sentence_end": false, "NEtag": "O"}, {"token": ".", "sentence_position": 42, "sentence_start": false, "sentence_end": true, "NEtag": "O"}], "sentence_chunktags": [["CS", "O"], ["PPSS", "B-NP"], ["BEDZ", "O"], ["VBG", "O"], ["NR", "O"], ["IN", "O"], ["PP$", "B-NP"], ["NN", "I-NP"], [",", "O"], ["PPSS", "B-NP"], ["VB", "O"], ["PPSS", "B-NP"], ["VB", "O"], ["TO", "O"], ["VB", "O"], ["CS", "O"], ["AT", "B-NP"], ["AP", "B-NP"], ["NN", "I-NP"], ["IN", "O"], ["RB", "O"], ["VBG", "O"], ["``", "I-NP"], ["VBZ", "O"], ["RB", "O"], ["IN", "O"], ["AT", "B-NP"], ["NN", "I-NP"], ["IN", "O"], ["JJ", "I-NP"], ["NNS", "I-NP"], ["WDT", "O"], ["MD", "O"], ["BE", "O"], ["VBN", "O"], ["IN", "O"], ["ABN", "O"], ["NNS", "I-NP"], [",", "O"], ["VBN", "O"], ["CC", "O"], ["VBG", "O"], [".", "O"]], "sentence_POS": [["As", "CS"], ["I", "PPSS"], ["was", "BEDZ"], ["saying", "VBG"], ["yesterday", "NR"], ["in", "IN"], ["our", "PP$"], ["meeting", "NN"], [",", ","], ["I", "PPSS"], ["think", "VB"], ["we", "PPSS"], ["need", "VB"], ["to", "TO"], ["understand", "VB"], ["that", "CS"], ["the", "AT"], ["only", "AP"], ["possibility", "NN"], ["of", "IN"], ["successfully", "RB"], ["approaching", "VBG"], ["globalization", "``"], ["lies", "VBZ"], ["precisely", "RB"], ["in", "IN"], ["the", "AT"], ["setting", "NN"], ["of", "IN"], ["common", "JJ"], ["rules", "NNS"], ["which", "WDT"], ["would", "MD"], ["be", "BE"], ["respected", "VBN"], ["by", "IN"], ["all", "ABN"], ["nations", "NNS"], [",", ","], ["developed", "VBN"], ["and", "CC"], ["developing", "VBG"], [".", "."]]}