{"sentence_LOW": ["While", "Icelanders", "enjoy", "the", "good", "fortune", "of", "having", "clean", ",", "renewable", "energy", "for", "70", "per", "cent", "of", "our", "total", "energy", "use", ",", "energy", "issues", "are", "increasingly", "becoming", "one", "of", "the", "main", "drivers", "of", "the", "sustainable", "development", "agenda", "within", "the", "United", "Nations", "."], "sentence_words": [{"token": "While", "sentence_position": 0, "sentence_start": true, "sentence_end": false, "NEtag": "O"}, {"token": "Icelanders", "sentence_position": 1, "sentence_start": false, "sentence_end": false, "NEtag": "I-MISC"}, {"token": "enjoy", "sentence_position": 2, "sentence_start": false, "sentence_end": false, "NEtag": "O"}, {"token": "the", "sentence_position": 3, "sentence_start": false, "sentence_end": false, "NEtag": "O"}, {"token": "good", "sentence_position": 4, "sentence_start": false, "sentence_end": false, "NEtag": "O"}, {"token": "fortune", "sentence_position": 5, "sentence_start": false, "sentence_end": false, "NEtag": "O"}, {"token": "of", "sentence_position": 6, "sentence_start": false, "sentence_end": false, "NEtag": "O"}, {"token": "having", "sentence_position": 7, "sentence_start": false, "sentence_end": false, "NEtag": "O"}, {"token": "clean", "sentence_position": 8, "sentence_start": false, "sentence_end": false, "NEtag": "O"}, {"token": ",", "sentence_position": 9, "sentence_start": false, "sentence_end": false, "NEtag": "O"}, {"token": "renewable", "sentence_position": 10, "sentence_start": false, "sentence_end": false, "NEtag": "O"}, {"token": "energy", "sentence_position": 11, "sentence_start": false, "sentence_end": false, "NEtag": "O"}, {"token": "for", "sentence_position": 12, "sentence_start": false, "sentence_end": false, "NEtag": "O"}, {"token": "70", "sentence_position": 13, "sentence_start": false, "sentence_end": false, "NEtag": "O"}, {"token": "per", "sentence_position": 14, "sentence_start": false, "sentence_end": false, "NEtag": "O"}, {"token": "cent", "sentence_position": 15, "sentence_start": false, "sentence_end": false, "NEtag": "O"}, {"token": "of", "sentence_position": 16, "sentence_start": false, "sentence_end": false, "NEtag": "O"}, {"token": "our", "sentence_position": 17, "sentence_start": false, "sentence_end": false, "NEtag": "O"}, {"token": "total", "sentence_position": 18, "sentence_start": false, "sentence_end": false, "NEtag": "O"}, {"token": "energy", "sentence_position": 19, "sentence_start": false, "sentence_end": false, "NEtag": "O"}, {"token": "use", "sentence_position": 20, "sentence_start": false, "sentence_end": false, "NEtag": "O"}, {"token": ",", "sentence_position": 21, "sentence_start": false, "sentence_end": false, "NEtag": "O"}, {"token": "energy", "sentence_position": 22, "sentence_start": false, "sentence_end": false, "NEtag": "O"}, {"token": "issues", "sentence_position": 23, "sentence_start": false, "sentence_end": false, "NEtag": "O"}, {"token": "are", "sentence_position": 24, "sentence_start": false, "sentence_end": false, "NEtag": "O"}, {"token": "increasingly", "sentence_position": 25, "sentence_start": false, "sentence_end": false, "NEtag": "O"}, {"token": "becoming", "sentence_position": 26, "sentence_start": false, "sentence_end": false, "NEtag": "O"}, {"token": "one", "sentence_position": 27, "sentence_start": false, "sentence_end": false, "NEtag": "O"}, {"token": "of", "sentence_position": 28, "sentence_start": false, "sentence_end": false, "NEtag": "O"}, {"token": "the", "sentence_position": 29, "sentence_start": false, "sentence_end": false, "NEtag": "O"}, {"token": "main", "sentence_position": 30, "sentence_start": false, "sentence_end": false, "NEtag": "O"}, {"token": "drivers", "sentence_position": 31, "sentence_start": false, "sentence_end": false, "NEtag": "O"}, {"token": "of", "sentence_position": 32, "sentence_start": false, "sentence_end": false, "NEtag": "O"}, {"token": "the", "sentence_position": 33, "sentence_start": false, "sentence_end": false, "NEtag": "O"}, {"token": "sustainable", "sentence_position": 34, "sentence_start": false, "sentence_end": false, "NEtag": "O"}, {"token": "development", "sentence_position": 35, "sentence_start": false, "sentence_end": false, "NEtag": "O"}, {"token": "agenda", "sentence_position": 36, "sentence_start": false, "sentence_end": false, "NEtag": "O"}, {"token": "within", "sentence_position": 37, "sentence_start": false, "sentence_end": false, "NEtag": "O"}, {"token": "the", "sentence_position": 38, "sentence_start": false, "sentence_end": false, "NEtag": "O"}, {"token": "United", "sentence_position": 39, "sentence_start": false, "sentence_end": false, "NEtag": "I-ORG"}, {"token": "Nations", "sentence_position": 40, "sentence_start": false, "sentence_end": false, "NEtag": "I-ORG"}, {"token": ".", "sentence_position": 41, "sentence_start": false, "sentence_end": true, "NEtag": "O"}], "sentence_chunktags": [["CS", "O"], ["NNS", "I-NP"], ["VB", "O"], ["AT", "B-NP"], ["JJ", "I-NP"], ["NN", "I-NP"], ["IN", "O"], ["HVG", "O"], ["JJ", "I-NP"], [",", "O"], ["JJ", "I-NP"], ["NN", "I-NP"], ["IN", "O"], ["CD", "O"], ["IN", "O"], ["NN", "I-NP"], ["IN", "O"], ["PP$", "B-NP"], ["NN", "I-NP"], ["NN", "I-NP"], ["NN", "I-NP"], [",", "O"], ["NN", "I-NP"], ["NNS", "I-NP"], ["BER", "O"], ["RB", "O"], ["VBG", "O"], ["CD", "O"], ["IN", "O"], ["AT", "B-NP"], ["JJS", "I-NP"], ["NNS", "I-NP"], ["IN", "O"], ["AT", "B-NP"], ["``", "I-NP"], ["NN", "I-NP"], ["NN", "I-NP"], ["IN", "O"], ["AT", "B-NP"], ["VBN-TL", "I-NP"], ["NNS-TL", "I-NP"], [".", "O"]], "sentence_POS": [["While", "CS"], ["Icelanders", "NNS"], ["enjoy", "VB"], ["the", "AT"], ["good", "JJ"], ["fortune", "NN"], ["of", "IN"], ["having", "HVG"], ["clean", "JJ"], [",", ","], ["renewable", "JJ"], ["energy", "NN"], ["for", "IN"], ["70", "CD"], ["per", "IN"], ["cent", "NN"], ["of", "IN"], ["our", "PP$"], ["total", "NN"], ["energy", "NN"], ["use", "NN"], [",", ","], ["energy", "NN"], ["issues", "NNS"], ["are", "BER"], ["increasingly", "RB"], ["becoming", "VBG"], ["one", "CD"], ["of", "IN"], ["the", "AT"], ["main", "JJS"], ["drivers", "NNS"], ["of", "IN"], ["the", "AT"], ["sustainable", "``"], ["development", "NN"], ["agenda", "NN"], ["within", "IN"], ["the", "AT"], ["United", "VBN-TL"], ["Nations", "NNS-TL"], [".", "."]]}