{"sentence_LOW": ["Only", "if", "we", "fund", "the", "human", "rights", "pillar", "properly", "can", "we", "achieve", "the", "results", "that", "we", "need", "and", "want", "from", "our", "world", "Organization", "."], "sentence_words": [{"token": "Only", "sentence_position": 0, "sentence_start": true, "sentence_end": false, "NEtag": "O"}, {"token": "if", "sentence_position": 1, "sentence_start": false, "sentence_end": false, "NEtag": "O"}, {"token": "we", "sentence_position": 2, "sentence_start": false, "sentence_end": false, "NEtag": "O"}, {"token": "fund", "sentence_position": 3, "sentence_start": false, "sentence_end": false, "NEtag": "O"}, {"token": "the", "sentence_position": 4, "sentence_start": false, "sentence_end": false, "NEtag": "O"}, {"token": "human", "sentence_position": 5, "sentence_start": false, "sentence_end": false, "NEtag": "O"}, {"token": "rights", "sentence_position": 6, "sentence_start": false, "sentence_end": false, "NEtag": "O"}, {"token": "pillar", "sentence_position": 7, "sentence_start": false, "sentence_end": false, "NEtag": "O"}, {"token": "properly", "sentence_position": 8, "sentence_start": false, "sentence_end": false, "NEtag": "O"}, {"token": "can", "sentence_position": 9, "sentence_start": false, "sentence_end": false, "NEtag": "O"}, {"token": "we", "sentence_position": 10, "sentence_start": false, "sentence_end": false, "NEtag": "O"}, {"token": "achieve", "sentence_position": 11, "sentence_start": false, "sentence_end": false, "NEtag": "O"}, {"token": "the", "sentence_position": 12, "sentence_start": false, "sentence_end": false, "NEtag": "O"}, {"token": "results", "sentence_position": 13, "sentence_start": false, "sentence_end": false, "NEtag": "O"}, {"token": "that", "sentence_position": 14, "sentence_start": false, "sentence_end": false, "NEtag": "O"}, {"token": "we", "sentence_position": 15, "sentence_start": false, "sentence_end": false, "NEtag": "O"}, {"token": "need", "sentence_position": 16, "sentence_start": false, "sentence_end": false, "NEtag": "O"}, {"token": "and", "sentence_position": 17, "sentence_start": false, "sentence_end": false, "NEtag": "O"}, {"token": "want", "sentence_position": 18, "sentence_start": false, "sentence_end": false, "NEtag": "O"}, {"token": "from", "sentence_position": 19, "sentence_start": false, "sentence_end": false, "NEtag": "O"}, {"token": "our", "sentence_position": 20, "sentence_start": false, "sentence_end": false, "NEtag": "O"}, {"token": "world", "sentence_position": 21, "sentence_start": false, "sentence_end": false, "NEtag": "O"}, {"token": "Organization", "sentence_position": 22, "sentence_start": false, "sentence_end": false, "NEtag": "O"}, {"token": ".", "sentence_position": 23, "sentence_start": false, "sentence_end": true, "NEtag": "O"}], "sentence_chunktags": [["RB", "O"], ["CS", "O"], ["PPSS", "B-NP"], ["NN", "I-NP"], ["AT", "B-NP"], ["JJ", "I-NP"], ["NNS", "I-NP"], ["NN", "I-NP"], ["RB", "O"], ["MD", "O"], ["PPSS", "B-NP"], ["VB", "O"], ["AT", "B-NP"], ["NNS", "I-NP"], ["WPS", "O"], ["PPSS", "B-NP"], ["VB", "O"], ["CC", "O"], ["VB", "O"], ["IN", "O"], ["PP$", "B-NP"], ["NN", "I-NP"], ["NN-TL", "I-NP"], [".", "O"]], "sentence_POS": [["Only", "RB"], ["if", "CS"], ["we", "PPSS"], ["fund", "NN"], ["the", "AT"], ["human", "JJ"], ["rights", "NNS"], ["pillar", "NN"], ["properly", "RB"], ["can", "MD"], ["we", "PPSS"], ["achieve", "VB"], ["the", "AT"], ["results", "NNS"], ["that", "WPS"], ["we", "PPSS"], ["need", "VB"], ["and", "CC"], ["want", "VB"], ["from", "IN"], ["our", "PP$"], ["world", "NN"], ["Organization", "NN-TL"], [".", "."]]}