{"sentence_LOW": ["The", "European", "Union", "wishes", "to", "enhance", "its", "interaction", "with", "the", "Muslim", "world", "through", "the", "Alliance", "of", "Civilizations", "and", "through", "cooperation", "in", "education", "and", "development", "by", "providing", "opportunities", "for", "the", "young", "."], "sentence_words": [{"token": "The", "sentence_position": 0, "sentence_start": true, "sentence_end": false, "NEtag": "O"}, {"token": "European", "sentence_position": 1, "sentence_start": false, "sentence_end": false, "NEtag": "I-ORG"}, {"token": "Union", "sentence_position": 2, "sentence_start": false, "sentence_end": false, "NEtag": "I-ORG"}, {"token": "wishes", "sentence_position": 3, "sentence_start": false, "sentence_end": false, "NEtag": "O"}, {"token": "to", "sentence_position": 4, "sentence_start": false, "sentence_end": false, "NEtag": "O"}, {"token": "enhance", "sentence_position": 5, "sentence_start": false, "sentence_end": false, "NEtag": "O"}, {"token": "its", "sentence_position": 6, "sentence_start": false, "sentence_end": false, "NEtag": "O"}, {"token": "interaction", "sentence_position": 7, "sentence_start": false, "sentence_end": false, "NEtag": "O"}, {"token": "with", "sentence_position": 8, "sentence_start": false, "sentence_end": false, "NEtag": "O"}, {"token": "the", "sentence_position": 9, "sentence_start": false, "sentence_end": false, "NEtag": "O"}, {"token": "Muslim", "sentence_position": 10, "sentence_start": false, "sentence_end": false, "NEtag": "I-MISC"}, {"token": "world", "sentence_position": 11, "sentence_start": false, "sentence_end": false, "NEtag": "O"}, {"token": "through", "sentence_position": 12, "sentence_start": false, "sentence_end": false, "NEtag": "O"}, {"token": "the", "sentence_position": 13, "sentence_start": false, "sentence_end": false, "NEtag": "O"}, {"token": "Alliance", "sentence_position": 14, "sentence_start": false, "sentence_end": false, "NEtag": "I-ORG"}, {"token": "of", "sentence_position": 15, "sentence_start": false, "sentence_end": false, "NEtag": "I-ORG"}, {"token": "Civilizations", "sentence_position": 16, "sentence_start": false, "sentence_end": false, "NEtag": "I-ORG"}, {"token": "and", "sentence_position": 17, "sentence_start": false, "sentence_end": false, "NEtag": "O"}, {"token": "through", "sentence_position": 18, "sentence_start": false, "sentence_end": false, "NEtag": "O"}, {"token": "cooperation", "sentence_position": 19, "sentence_start": false, "sentence_end": false, "NEtag": "O"}, {"token": "in", "sentence_position": 20, "sentence_start": false, "sentence_end": false, "NEtag": "O"}, {"token": "education", "sentence_position": 21, "sentence_start": false, "sentence_end": false, "NEtag": "O"}, {"token": "and", "sentence_position": 22, "sentence_start": false, "sentence_end": false, "NEtag": "O"}, {"token": "development", "sentence_position": 23, "sentence_start": false, "sentence_end": false, "NEtag": "O"}, {"token": "by", "sentence_position": 24, "sentence_start": false, "sentence_end": false, "NEtag": "O"}, {"token": "providing", "sentence_position": 25, "sentence_start": false, "sentence_end": false, "NEtag": "O"}, {"token": "opportunities", "sentence_position": 26, "sentence_start": false, "sentence_end": false, "NEtag": "O"}, {"token": "for", "sentence_position": 27, "sentence_start": false, "sentence_end": false, "NEtag": "O"}, {"token": "the", "sentence_position": 28, "sentence_start": false, "sentence_end": false, "NEtag": "O"}, {"token": "young", "sentence_position": 29, "sentence_start": false, "sentence_end": false, "NEtag": "O"}, {"token": ".", "sentence_position": 30, "sentence_start": false, "sentence_end": true, "NEtag": "O"}], "sentence_chunktags": [["AT", "B-NP"], ["JJ", "I-NP"], ["NN", "I-NP"], ["VBZ", "O"], ["TO", "O"], ["VB", "O"], ["PP$", "B-NP"], ["NN", "I-NP"], ["IN", "O"], ["AT", "B-NP"], ["JJ", "I-NP"], ["NN", "I-NP"], ["IN", "O"], ["AT", "B-NP"], ["NN-TL", "I-NP"], ["IN-TL", "O"], ["NNS", "I-NP"], ["CC", "O"], ["IN", "O"], ["NN", "I-NP"], ["IN", "O"], ["NN", "I-NP"], ["CC", "O"], ["NN", "I-NP"], ["IN", "O"], ["VBG", "O"], ["NNS", "I-NP"], ["IN", "O"], ["AT", "B-NP"], ["JJ", "I-NP"], [".", "O"]], "sentence_POS": [["The", "AT"], ["European", "JJ"], ["Union", "NN"], ["wishes", "VBZ"], ["to", "TO"], ["enhance", "VB"], ["its", "PP$"], ["interaction", "NN"], ["with", "IN"], ["the", "AT"], ["Muslim", "JJ"], ["world", "NN"], ["through", "IN"], ["the", "AT"], ["Alliance", "NN-TL"], ["of", "IN-TL"], ["Civilizations", "NNS"], ["and", "CC"], ["through", "IN"], ["cooperation", "NN"], ["in", "IN"], ["education", "NN"], ["and", "CC"], ["development", "NN"], ["by", "IN"], ["providing", "VBG"], ["opportunities", "NNS"], ["for", "IN"], ["the", "AT"], ["young", "JJ"], [".", "."]]}