{"sentence_LOW": ["Terrorism", "did", "not", "start", "on", "11", "September", "."], "sentence_words": [{"token": "Terrorism", "sentence_position": 0, "sentence_start": true, "sentence_end": false, "NEtag": "O"}, {"token": "did", "sentence_position": 1, "sentence_start": false, "sentence_end": false, "NEtag": "O"}, {"token": "not", "sentence_position": 2, "sentence_start": false, "sentence_end": false, "NEtag": "O"}, {"token": "start", "sentence_position": 3, "sentence_start": false, "sentence_end": false, "NEtag": "O"}, {"token": "on", "sentence_position": 4, "sentence_start": false, "sentence_end": false, "NEtag": "O"}, {"token": "11", "sentence_position": 5, "sentence_start": false, "sentence_end": false, "NEtag": "O"}, {"token": "September", "sentence_position": 6, "sentence_start": false, "sentence_end": false, "NEtag": "O"}, {"token": ".", "sentence_position": 7, "sentence_start": false, "sentence_end": true, "NEtag": "O"}], "sentence_chunktags": [["``", "I-NP"], ["DOD", null], ["*", "O"], ["VB", "O"], ["IN", "O"], ["CD", "O"], ["NP", "B-NP"], [".", "O"]], "sentence_POS": [["Terrorism", "``"], ["did", "DOD"], ["not", "*"], ["start", "VB"], ["on", "IN"], ["11", "CD"], ["September", "NP"], [".", "."]]}