{"sentence_LOW": ["Mongolia", "believes", "that", "the", "Fund", "should", "serve", "as", "a", "vital", "instrument", "to", "assist", "Member", "States", "in", "the", "consolidation", "of", "democracy", "and", "implementation", "of", "their", "commitments", ",", "including", "the", "Ulaanbaatar", "Declaration", "and", "Plan", "of", "Action", "adopted", "at", "the", "fifth", "International", "Conference", "of", "New", "or", "Restored", "Democracies", "in", "2003", "and", "approved", "by", "the", "General", "Assembly", "in", "its", "resolution", "58/13", "."], "sentence_words": [{"token": "Mongolia", "sentence_position": 0, "sentence_start": true, "sentence_end": false, "NEtag": "I-LOC"}, {"token": "believes", "sentence_position": 1, "sentence_start": false, "sentence_end": false, "NEtag": "O"}, {"token": "that", "sentence_position": 2, "sentence_start": false, "sentence_end": false, "NEtag": "O"}, {"token": "the", "sentence_position": 3, "sentence_start": false, "sentence_end": false, "NEtag": "O"}, {"token": "Fund", "sentence_position": 4, "sentence_start": false, "sentence_end": false, "NEtag": "O"}, {"token": "should", "sentence_position": 5, "sentence_start": false, "sentence_end": false, "NEtag": "O"}, {"token": "serve", "sentence_position": 6, "sentence_start": false, "sentence_end": false, "NEtag": "O"}, {"token": "as", "sentence_position": 7, "sentence_start": false, "sentence_end": false, "NEtag": "O"}, {"token": "a", "sentence_position": 8, "sentence_start": false, "sentence_end": false, "NEtag": "O"}, {"token": "vital", "sentence_position": 9, "sentence_start": false, "sentence_end": false, "NEtag": "O"}, {"token": "instrument", "sentence_position": 10, "sentence_start": false, "sentence_end": false, "NEtag": "O"}, {"token": "to", "sentence_position": 11, "sentence_start": false, "sentence_end": false, "NEtag": "O"}, {"token": "assist", "sentence_position": 12, "sentence_start": false, "sentence_end": false, "NEtag": "O"}, {"token": "Member", "sentence_position": 13, "sentence_start": false, "sentence_end": false, "NEtag": "O"}, {"token": "States", "sentence_position": 14, "sentence_start": false, "sentence_end": false, "NEtag": "O"}, {"token": "in", "sentence_position": 15, "sentence_start": false, "sentence_end": false, "NEtag": "O"}, {"token": "the", "sentence_position": 16, "sentence_start": false, "sentence_end": false, "NEtag": "O"}, {"token": "consolidation", "sentence_position": 17, "sentence_start": false, "sentence_end": false, "NEtag": "O"}, {"token": "of", "sentence_position": 18, "sentence_start": false, "sentence_end": false, "NEtag": "O"}, {"token": "democracy", "sentence_position": 19, "sentence_start": false, "sentence_end": false, "NEtag": "O"}, {"token": "and", "sentence_position": 20, "sentence_start": false, "sentence_end": false, "NEtag": "O"}, {"token": "implementation", "sentence_position": 21, "sentence_start": false, "sentence_end": false, "NEtag": "O"}, {"token": "of", "sentence_position": 22, "sentence_start": false, "sentence_end": false, "NEtag": "O"}, {"token": "their", "sentence_position": 23, "sentence_start": false, "sentence_end": false, "NEtag": "O"}, {"token": "commitments", "sentence_position": 24, "sentence_start": false, "sentence_end": false, "NEtag": "O"}, {"token": ",", "sentence_position": 25, "sentence_start": false, "sentence_end": false, "NEtag": "O"}, {"token": "including", "sentence_position": 26, "sentence_start": false, "sentence_end": false, "NEtag": "O"}, {"token": "the", "sentence_position": 27, "sentence_start": false, "sentence_end": false, "NEtag": "O"}, {"token": "Ulaanbaatar", "sentence_position": 28, "sentence_start": false, "sentence_end": false, "NEtag": "I-LOC"}, {"token": "Declaration", "sentence_position": 29, "sentence_start": false, "sentence_end": false, "NEtag": "I-MISC"}, {"token": "and", "sentence_position": 30, "sentence_start": false, "sentence_end": false, "NEtag": "O"}, {"token": "Plan", "sentence_position": 31, "sentence_start": false, "sentence_end": false, "NEtag": "I-MISC"}, {"token": "of", "sentence_position": 32, "sentence_start": false, "sentence_end": false, "NEtag": "I-MISC"}, {"token": "Action", "sentence_position": 33, "sentence_start": false, "sentence_end": false, "NEtag": "I-MISC"}, {"token": "adopted", "sentence_position": 34, "sentence_start": false, "sentence_end": false, "NEtag": "O"}, {"token": "at", "sentence_position": 35, "sentence_start": false, "sentence_end": false, "NEtag": "O"}, {"token": "the", "sentence_position": 36, "sentence_start": false, "sentence_end": false, "NEtag": "O"}, {"token": "fifth", "sentence_position": 37, "sentence_start": false, "sentence_end": false, "NEtag": "O"}, {"token": "International", "sentence_position": 38, "sentence_start": false, "sentence_end": false, "NEtag": "I-MISC"}, {"token": "Conference", "sentence_position": 39, "sentence_start": false, "sentence_end": false, "NEtag": "I-MISC"}, {"token": "of", "sentence_position": 40, "sentence_start": false, "sentence_end": false, "NEtag": "I-MISC"}, {"token": "New", "sentence_position": 41, "sentence_start": false, "sentence_end": false, "NEtag": "I-MISC"}, {"token": "or", "sentence_position": 42, "sentence_start": false, "sentence_end": false, "NEtag": "I-MISC"}, {"token": "Restored", "sentence_position": 43, "sentence_start": false, "sentence_end": false, "NEtag": "I-MISC"}, {"token": "Democracies", "sentence_position": 44, "sentence_start": false, "sentence_end": false, "NEtag": "I-MISC"}, {"token": "in", "sentence_position": 45, "sentence_start": false, "sentence_end": false, "NEtag": "O"}, {"token": "2003", "sentence_position": 46, "sentence_start": false, "sentence_end": false, "NEtag": "O"}, {"token": "and", "sentence_position": 47, "sentence_start": false, "sentence_end": false, "NEtag": "O"}, {"token": "approved", "sentence_position": 48, "sentence_start": false, "sentence_end": false, "NEtag": "O"}, {"token": "by", "sentence_position": 49, "sentence_start": false, "sentence_end": false, "NEtag": "O"}, {"token": "the", "sentence_position": 50, "sentence_start": false, "sentence_end": false, "NEtag": "O"}, {"token": "General", "sentence_position": 51, "sentence_start": false, "sentence_end": false, "NEtag": "I-ORG"}, {"token": "Assembly", "sentence_position": 52, "sentence_start": false, "sentence_end": false, "NEtag": "I-ORG"}, {"token": "in", "sentence_position": 53, "sentence_start": false, "sentence_end": false, "NEtag": "O"}, {"token": "its", "sentence_position": 54, "sentence_start": false, "sentence_end": false, "NEtag": "O"}, {"token": "resolution", "sentence_position": 55, "sentence_start": false, "sentence_end": false, "NEtag": "O"}, {"token": "58/13", "sentence_position": 56, "sentence_start": false, "sentence_end": false, "NEtag": "O"}, {"token": ".", "sentence_position": 57, "sentence_start": false, "sentence_end": true, "NEtag": "O"}], "chunk_tags": [["NP-TL", "I-NP"], ["VBZ", "O"], ["CS", "O"], ["AT", "B-NP"], ["NN-TL", "I-NP"], ["MD", "O"], ["VB", "O"], ["CS", "O"], ["AT", "B-NP"], ["JJ", "I-NP"], ["NN", "I-NP"], ["IN", "O"], ["VB", "O"], ["NN-TL", "I-NP"], ["NNS-TL", "I-NP"], ["IN", "O"], ["AT", "B-NP"], ["NN", "I-NP"], ["IN", "O"], ["NN", "I-NP"], ["CC", "O"], ["NN", "I-NP"], ["IN", "O"], ["PP$", "B-NP"], ["NNS", "I-NP"], [",", "O"], ["IN", "O"], ["AT", "B-NP"], ["``", "I-NP"], ["NN-TL", "I-NP"], ["CC", "O"], ["NN-TL", "I-NP"], ["IN-TL", "O"], ["NN-TL", "I-NP"], ["VBD", "O"], ["IN", "O"], ["AT", "B-NP"], ["OD", "I-NP"], ["JJ-TL", "I-NP"], ["NN-TL", "I-NP"], ["IN-TL", "O"], ["JJ-TL", "I-NP"], ["CC", "O"], ["VBD", "O"], ["VBZ", "O"], ["IN", "O"], ["CD", "O"], ["CC", "O"], ["VBD", "O"], ["IN", "O"], ["AT", "B-NP"], ["JJ-TL", "I-NP"], ["NN-TL", "I-NP"], ["IN", "O"], ["PP$", "B-NP"], ["NN", "I-NP"], ["CD", "O"], [".", "O"]], "sentence_POS": [["Mongolia", "NP-TL"], ["believes", "VBZ"], ["that", "CS"], ["the", "AT"], ["Fund", "NN-TL"], ["should", "MD"], ["serve", "VB"], ["as", "CS"], ["a", "AT"], ["vital", "JJ"], ["instrument", "NN"], ["to", "IN"], ["assist", "VB"], ["Member", "NN-TL"], ["States", "NNS-TL"], ["in", "IN"], ["the", "AT"], ["consolidation", "NN"], ["of", "IN"], ["democracy", "NN"], ["and", "CC"], ["implementation", "NN"], ["of", "IN"], ["their", "PP$"], ["commitments", "NNS"], [",", ","], ["including", "IN"], ["the", "AT"], ["Ulaanbaatar", "``"], ["Declaration", "NN-TL"], ["and", "CC"], ["Plan", "NN-TL"], ["of", "IN-TL"], ["Action", "NN-TL"], ["adopted", "VBD"], ["at", "IN"], ["the", "AT"], ["fifth", "OD"], ["International", "JJ-TL"], ["Conference", "NN-TL"], ["of", "IN-TL"], ["New", "JJ-TL"], ["or", "CC"], ["Restored", "VBD"], ["Democracies", "VBZ"], ["in", "IN"], ["2003", "CD"], ["and", "CC"], ["approved", "VBD"], ["by", "IN"], ["the", "AT"], ["General", "JJ-TL"], ["Assembly", "NN-TL"], ["in", "IN"], ["its", "PP$"], ["resolution", "NN"], ["58/13", "CD"], [".", "."]]}