{"sentence_LOW": ["Accountability", ",", "oversight", ",", "management", "performance", "and", "transparency", "of", "the", "Secretariat", "must", "be", "brought", "to", "a", "new", "level", "of", "efficiency", ",", "professionalism", "and", "ethical", "conduct", "on", "a", "par", "with", "the", "best", "corporate", "governance", "practices", "."], "sentence_words": [{"token": "Accountability", "sentence_position": 0, "sentence_start": true, "sentence_end": false, "NEtag": "O"}, {"token": ",", "sentence_position": 1, "sentence_start": false, "sentence_end": false, "NEtag": "O"}, {"token": "oversight", "sentence_position": 2, "sentence_start": false, "sentence_end": false, "NEtag": "O"}, {"token": ",", "sentence_position": 3, "sentence_start": false, "sentence_end": false, "NEtag": "O"}, {"token": "management", "sentence_position": 4, "sentence_start": false, "sentence_end": false, "NEtag": "O"}, {"token": "performance", "sentence_position": 5, "sentence_start": false, "sentence_end": false, "NEtag": "O"}, {"token": "and", "sentence_position": 6, "sentence_start": false, "sentence_end": false, "NEtag": "O"}, {"token": "transparency", "sentence_position": 7, "sentence_start": false, "sentence_end": false, "NEtag": "O"}, {"token": "of", "sentence_position": 8, "sentence_start": false, "sentence_end": false, "NEtag": "O"}, {"token": "the", "sentence_position": 9, "sentence_start": false, "sentence_end": false, "NEtag": "O"}, {"token": "Secretariat", "sentence_position": 10, "sentence_start": false, "sentence_end": false, "NEtag": "O"}, {"token": "must", "sentence_position": 11, "sentence_start": false, "sentence_end": false, "NEtag": "O"}, {"token": "be", "sentence_position": 12, "sentence_start": false, "sentence_end": false, "NEtag": "O"}, {"token": "brought", "sentence_position": 13, "sentence_start": false, "sentence_end": false, "NEtag": "O"}, {"token": "to", "sentence_position": 14, "sentence_start": false, "sentence_end": false, "NEtag": "O"}, {"token": "a", "sentence_position": 15, "sentence_start": false, "sentence_end": false, "NEtag": "O"}, {"token": "new", "sentence_position": 16, "sentence_start": false, "sentence_end": false, "NEtag": "O"}, {"token": "level", "sentence_position": 17, "sentence_start": false, "sentence_end": false, "NEtag": "O"}, {"token": "of", "sentence_position": 18, "sentence_start": false, "sentence_end": false, "NEtag": "O"}, {"token": "efficiency", "sentence_position": 19, "sentence_start": false, "sentence_end": false, "NEtag": "O"}, {"token": ",", "sentence_position": 20, "sentence_start": false, "sentence_end": false, "NEtag": "O"}, {"token": "professionalism", "sentence_position": 21, "sentence_start": false, "sentence_end": false, "NEtag": "O"}, {"token": "and", "sentence_position": 22, "sentence_start": false, "sentence_end": false, "NEtag": "O"}, {"token": "ethical", "sentence_position": 23, "sentence_start": false, "sentence_end": false, "NEtag": "O"}, {"token": "conduct", "sentence_position": 24, "sentence_start": false, "sentence_end": false, "NEtag": "O"}, {"token": "on", "sentence_position": 25, "sentence_start": false, "sentence_end": false, "NEtag": "O"}, {"token": "a", "sentence_position": 26, "sentence_start": false, "sentence_end": false, "NEtag": "O"}, {"token": "par", "sentence_position": 27, "sentence_start": false, "sentence_end": false, "NEtag": "O"}, {"token": "with", "sentence_position": 28, "sentence_start": false, "sentence_end": false, "NEtag": "O"}, {"token": "the", "sentence_position": 29, "sentence_start": false, "sentence_end": false, "NEtag": "O"}, {"token": "best", "sentence_position": 30, "sentence_start": false, "sentence_end": false, "NEtag": "O"}, {"token": "corporate", "sentence_position": 31, "sentence_start": false, "sentence_end": false, "NEtag": "O"}, {"token": "governance", "sentence_position": 32, "sentence_start": false, "sentence_end": false, "NEtag": "O"}, {"token": "practices", "sentence_position": 33, "sentence_start": false, "sentence_end": false, "NEtag": "O"}, {"token": ".", "sentence_position": 34, "sentence_start": false, "sentence_end": true, "NEtag": "O"}], "sentence_chunktags": [["``", "I-NP"], [",", "O"], ["NN", "I-NP"], [",", "O"], ["NN", "I-NP"], ["NN", "I-NP"], ["CC", "O"], ["NN", "I-NP"], ["IN", "O"], ["AT", "B-NP"], ["NN-TL", "I-NP"], ["MD", "O"], ["BE", "O"], ["VBN", "O"], ["TO", "O"], ["AT", "B-NP"], ["JJ", "I-NP"], ["NN", "I-NP"], ["IN", "O"], ["NN", "I-NP"], [",", "O"], ["NN-HL", "I-NP"], ["CC-HL", null], ["JJ", "I-NP"], ["NN", "I-NP"], ["IN", "O"], ["AT", "B-NP"], ["NN", "I-NP"], ["IN", "O"], ["AT", "B-NP"], ["JJT", "I-NP"], ["JJ", "I-NP"], ["``", "I-NP"], ["NNS", "I-NP"], [".", "O"]], "sentence_POS": [["Accountability", "``"], [",", ","], ["oversight", "NN"], [",", ","], ["management", "NN"], ["performance", "NN"], ["and", "CC"], ["transparency", "NN"], ["of", "IN"], ["the", "AT"], ["Secretariat", "NN-TL"], ["must", "MD"], ["be", "BE"], ["brought", "VBN"], ["to", "TO"], ["a", "AT"], ["new", "JJ"], ["level", "NN"], ["of", "IN"], ["efficiency", "NN"], [",", ","], ["professionalism", "NN-HL"], ["and", "CC-HL"], ["ethical", "JJ"], ["conduct", "NN"], ["on", "IN"], ["a", "AT"], ["par", "NN"], ["with", "IN"], ["the", "AT"], ["best", "JJT"], ["corporate", "JJ"], ["governance", "``"], ["practices", "NNS"], [".", "."]]}