{"sentence_LOW": ["As", "a", "result", ",", "since", "then", "there", "has", "not", "been", "a", "single", "death", ",", "a", "single", "wound", "or", "a", "single", "bullet", "fired", "in", "the", "conflict", "with", "FARC", ".", "The", "Agreement", "will", "be", "officially", "signed", "in", "Cartagena", "de", "Indias", "on", "26", "September", "."], "sentence_words": [{"token": "As", "sentence_position": 0, "sentence_start": true, "sentence_end": false, "NEtag": "O"}, {"token": "a", "sentence_position": 1, "sentence_start": false, "sentence_end": false, "NEtag": "O"}, {"token": "result", "sentence_position": 2, "sentence_start": false, "sentence_end": false, "NEtag": "O"}, {"token": ",", "sentence_position": 3, "sentence_start": false, "sentence_end": false, "NEtag": "O"}, {"token": "since", "sentence_position": 4, "sentence_start": false, "sentence_end": false, "NEtag": "O"}, {"token": "then", "sentence_position": 5, "sentence_start": false, "sentence_end": false, "NEtag": "O"}, {"token": "there", "sentence_position": 6, "sentence_start": false, "sentence_end": false, "NEtag": "O"}, {"token": "has", "sentence_position": 7, "sentence_start": false, "sentence_end": false, "NEtag": "O"}, {"token": "not", "sentence_position": 8, "sentence_start": false, "sentence_end": false, "NEtag": "O"}, {"token": "been", "sentence_position": 9, "sentence_start": false, "sentence_end": false, "NEtag": "O"}, {"token": "a", "sentence_position": 10, "sentence_start": false, "sentence_end": false, "NEtag": "O"}, {"token": "single", "sentence_position": 11, "sentence_start": false, "sentence_end": false, "NEtag": "O"}, {"token": "death", "sentence_position": 12, "sentence_start": false, "sentence_end": false, "NEtag": "O"}, {"token": ",", "sentence_position": 13, "sentence_start": false, "sentence_end": false, "NEtag": "O"}, {"token": "a", "sentence_position": 14, "sentence_start": false, "sentence_end": false, "NEtag": "O"}, {"token": "single", "sentence_position": 15, "sentence_start": false, "sentence_end": false, "NEtag": "O"}, {"token": "wound", "sentence_position": 16, "sentence_start": false, "sentence_end": false, "NEtag": "O"}, {"token": "or", "sentence_position": 17, "sentence_start": false, "sentence_end": false, "NEtag": "O"}, {"token": "a", "sentence_position": 18, "sentence_start": false, "sentence_end": false, "NEtag": "O"}, {"token": "single", "sentence_position": 19, "sentence_start": false, "sentence_end": false, "NEtag": "O"}, {"token": "bullet", "sentence_position": 20, "sentence_start": false, "sentence_end": false, "NEtag": "O"}, {"token": "fired", "sentence_position": 21, "sentence_start": false, "sentence_end": false, "NEtag": "O"}, {"token": "in", "sentence_position": 22, "sentence_start": false, "sentence_end": false, "NEtag": "O"}, {"token": "the", "sentence_position": 23, "sentence_start": false, "sentence_end": false, "NEtag": "O"}, {"token": "conflict", "sentence_position": 24, "sentence_start": false, "sentence_end": false, "NEtag": "O"}, {"token": "with", "sentence_position": 25, "sentence_start": false, "sentence_end": false, "NEtag": "O"}, {"token": "FARC", "sentence_position": 26, "sentence_start": false, "sentence_end": false, "NEtag": "I-ORG"}, {"token": ".", "sentence_position": 27, "sentence_start": false, "sentence_end": false, "NEtag": "O"}, {"token": "The", "sentence_position": 28, "sentence_start": false, "sentence_end": false, "NEtag": "O"}, {"token": "Agreement", "sentence_position": 29, "sentence_start": false, "sentence_end": false, "NEtag": "O"}, {"token": "will", "sentence_position": 30, "sentence_start": false, "sentence_end": false, "NEtag": "O"}, {"token": "be", "sentence_position": 31, "sentence_start": false, "sentence_end": false, "NEtag": "O"}, {"token": "officially", "sentence_position": 32, "sentence_start": false, "sentence_end": false, "NEtag": "O"}, {"token": "signed", "sentence_position": 33, "sentence_start": false, "sentence_end": false, "NEtag": "O"}, {"token": "in", "sentence_position": 34, "sentence_start": false, "sentence_end": false, "NEtag": "O"}, {"token": "Cartagena", "sentence_position": 35, "sentence_start": false, "sentence_end": false, "NEtag": "I-LOC"}, {"token": "de", "sentence_position": 36, "sentence_start": false, "sentence_end": false, "NEtag": "I-LOC"}, {"token": "Indias", "sentence_position": 37, "sentence_start": false, "sentence_end": false, "NEtag": "I-LOC"}, {"token": "on", "sentence_position": 38, "sentence_start": false, "sentence_end": false, "NEtag": "O"}, {"token": "26", "sentence_position": 39, "sentence_start": false, "sentence_end": false, "NEtag": "O"}, {"token": "September", "sentence_position": 40, "sentence_start": false, "sentence_end": false, "NEtag": "O"}, {"token": ".", "sentence_position": 41, "sentence_start": false, "sentence_end": true, "NEtag": "O"}], "chunk_tags": [["CS", "O"], ["AT", "B-NP"], ["NN", "I-NP"], [",", "O"], ["CS", "O"], ["RB", "O"], ["EX", "O"], ["HVZ", "O"], ["*", "O"], ["BEN", "O"], ["AT", "B-NP"], ["AP", "B-NP"], ["NN", "I-NP"], [",", "O"], ["AT", "B-NP"], ["AP", "B-NP"], ["NN", "I-NP"], ["CC", "O"], ["AT", "B-NP"], ["AP", "B-NP"], ["NN", "I-NP"], ["VBN", "O"], ["IN", "O"], ["AT", "B-NP"], ["NN", "I-NP"], ["IN", "O"], ["``", "I-NP"], [".", "O"], ["AT", "B-NP"], ["NN-TL", "I-NP"], ["MD", "O"], ["BE", "O"], ["RB", "O"], ["VBN", "O"], ["IN", "O"], ["``", "I-NP"], ["FW-IN", null], ["NNS", "I-NP"], ["IN", "O"], ["CD", "O"], ["NP", "B-NP"], [".", "O"]], "sentence_POS": [["As", "CS"], ["a", "AT"], ["result", "NN"], [",", ","], ["since", "CS"], ["then", "RB"], ["there", "EX"], ["has", "HVZ"], ["not", "*"], ["been", "BEN"], ["a", "AT"], ["single", "AP"], ["death", "NN"], [",", ","], ["a", "AT"], ["single", "AP"], ["wound", "NN"], ["or", "CC"], ["a", "AT"], ["single", "AP"], ["bullet", "NN"], ["fired", "VBN"], ["in", "IN"], ["the", "AT"], ["conflict", "NN"], ["with", "IN"], ["FARC", "``"], [".", "."], ["The", "AT"], ["Agreement", "NN-TL"], ["will", "MD"], ["be", "BE"], ["officially", "RB"], ["signed", "VBN"], ["in", "IN"], ["Cartagena", "``"], ["de", "FW-IN"], ["Indias", "NNS"], ["on", "IN"], ["26", "CD"], ["September", "NP"], [".", "."]]}