[{"token": "The", "sentence_position": 0, "sentence_start": true, "sentence_end": false, "NEtag": "O", "case": "upper", "last_char": "e", "geoText_loc": false, "known_org": false, "known_prog": false, "hyphen": false, "prev_token": null, "next_token": "risk", "pos": "AT", "chunktag": "B-NP", "prev_pos": null, "prev_chunktag": null, "next_pos": "NN", "next_chunktag": "I-NP"}, {"token": "risk", "sentence_position": 1, "sentence_start": false, "sentence_end": false, "NEtag": "O", "case": "lower", "last_char": "k", "geoText_loc": false, "known_org": false, "known_prog": false, "hyphen": false, "prev_token": "The", "next_token": "posed", "pos": "NN", "chunktag": "I-NP", "prev_pos": "AT", "prev_chunktag": "B-NP", "next_pos": "VBN", "next_chunktag": "O"}, {"token": "posed", "sentence_position": 2, "sentence_start": false, "sentence_end": false, "NEtag": "O", "case": "lower", "last_char": "d", "geoText_loc": false, "known_org": false, "known_prog": false, "hyphen": false, "prev_token": "risk", "next_token": "by", "pos": "VBN", "chunktag": "O", "prev_pos": "NN", "prev_chunktag": "I-NP", "next_pos": "IN", "next_chunktag": "O"}, {"token": "by", "sentence_position": 3, "sentence_start": false, "sentence_end": false, "NEtag": "O", "case": "lower", "last_char": "y", "geoText_loc": false, "known_org": false, "known_prog": false, "hyphen": false, "prev_token": "posed", "next_token": "the", "pos": "IN", "chunktag": "O", "prev_pos": "VBN", "prev_chunktag": "O", "next_pos": "AT", "next_chunktag": "B-NP"}, {"token": "the", "sentence_position": 4, "sentence_start": false, "sentence_end": false, "NEtag": "O", "case": "lower", "last_char": "e", "geoText_loc": false, "known_org": false, "known_prog": false, "hyphen": false, "prev_token": "by", "next_token": "intersection", "pos": "AT", "chunktag": "B-NP", "prev_pos": "IN", "prev_chunktag": "O", "next_pos": "NN", "next_chunktag": "I-NP"}, {"token": "intersection", "sentence_position": 5, "sentence_start": false, "sentence_end": false, "NEtag": "O", "case": "lower", "last_char": "n", "geoText_loc": false, "known_org": false, "known_prog": false, "hyphen": false, "prev_token": "the", "next_token": "between", "pos": "NN", "chunktag": "I-NP", "prev_pos": "AT", "prev_chunktag": "B-NP", "next_pos": "IN", "next_chunktag": "O"}, {"token": "between", "sentence_position": 6, "sentence_start": false, "sentence_end": false, "NEtag": "O", "case": "lower", "last_char": "n", "geoText_loc": false, "known_org": false, "known_prog": false, "hyphen": false, "prev_token": "intersection", "next_token": "proliferation", "pos": "IN", "chunktag": "O", "prev_pos": "NN", "prev_chunktag": "I-NP", "next_pos": "NN", "next_chunktag": "I-NP"}, {"token": "proliferation", "sentence_position": 7, "sentence_start": false, "sentence_end": false, "NEtag": "O", "case": "lower", "last_char": "n", "geoText_loc": false, "known_org": false, "known_prog": false, "hyphen": false, "prev_token": "between", "next_token": "and", "pos": "NN", "chunktag": "I-NP", "prev_pos": "IN", "prev_chunktag": "O", "next_pos": "CC", "next_chunktag": "O"}, {"token": "and", "sentence_position": 8, "sentence_start": false, "sentence_end": false, "NEtag": "O", "case": "lower", "last_char": "d", "geoText_loc": false, "known_org": false, "known_prog": false, "hyphen": false, "prev_token": "proliferation", "next_token": "terrorism", "pos": "CC", "chunktag": "O", "prev_pos": "NN", "prev_chunktag": "I-NP", "next_pos": "``", "next_chunktag": "I-NP"}, {"token": "terrorism", "sentence_position": 9, "sentence_start": false, "sentence_end": false, "NEtag": "O", "case": "lower", "last_char": "m", "geoText_loc": false, "known_org": false, "known_prog": false, "hyphen": false, "prev_token": "and", "next_token": "is", "pos": "``", "chunktag": "I-NP", "prev_pos": "CC", "prev_chunktag": "O", "next_pos": "BEZ", "next_chunktag": "O"}, {"token": "is", "sentence_position": 10, "sentence_start": false, "sentence_end": false, "NEtag": "O", "case": "lower", "last_char": "s", "geoText_loc": false, "known_org": false, "known_prog": false, "hyphen": false, "prev_token": "terrorism", "next_token": "real", "pos": "BEZ", "chunktag": "O", "prev_pos": "``", "prev_chunktag": "I-NP", "next_pos": "JJ", "next_chunktag": "I-NP"}, {"token": "real", "sentence_position": 11, "sentence_start": false, "sentence_end": false, "NEtag": "O", "case": "lower", "last_char": "l", "geoText_loc": false, "known_org": false, "known_prog": false, "hyphen": false, "prev_token": "is", "next_token": "and", "pos": "JJ", "chunktag": "I-NP", "prev_pos": "BEZ", "prev_chunktag": "O", "next_pos": "CC", "next_chunktag": "O"}, {"token": "and", "sentence_position": 12, "sentence_start": false, "sentence_end": false, "NEtag": "O", "case": "lower", "last_char": "d", "geoText_loc": false, "known_org": false, "known_prog": false, "hyphen": false, "prev_token": "real", "next_token": "serious", "pos": "CC", "chunktag": "O", "prev_pos": "JJ", "prev_chunktag": "I-NP", "next_pos": "JJ", "next_chunktag": "I-NP"}, {"token": "serious", "sentence_position": 13, "sentence_start": false, "sentence_end": false, "NEtag": "O", "case": "lower", "last_char": "s", "geoText_loc": false, "known_org": false, "known_prog": false, "hyphen": false, "prev_token": "and", "next_token": ".", "pos": "JJ", "chunktag": "I-NP", "prev_pos": "CC", "prev_chunktag": "O", "next_pos": ".", "next_chunktag": "O"}, {"token": ".", "sentence_position": 14, "sentence_start": false, "sentence_end": true, "NEtag": "O", "case": "lower", "last_char": ".", "geoText_loc": false, "known_org": false, "known_prog": false, "hyphen": false, "prev_token": "serious", "next_token": null, "pos": ".", "chunktag": "O", "prev_pos": "JJ", "prev_chunktag": "I-NP", "next_pos": null, "next_chunktag": null}]