{"sentence_LOW": ["We", "are", "hopeful", "that", "the", "parties", "will", "soon", "be", "able", "to", "embark", "on", "negotiations", "towards", "an", "interim", "administration", "for", "the", "North-East", "Province", "."], "sentence_words": [{"token": "We", "sentence_position": 0, "sentence_start": true, "sentence_end": false, "NEtag": "O"}, {"token": "are", "sentence_position": 1, "sentence_start": false, "sentence_end": false, "NEtag": "O"}, {"token": "hopeful", "sentence_position": 2, "sentence_start": false, "sentence_end": false, "NEtag": "O"}, {"token": "that", "sentence_position": 3, "sentence_start": false, "sentence_end": false, "NEtag": "O"}, {"token": "the", "sentence_position": 4, "sentence_start": false, "sentence_end": false, "NEtag": "O"}, {"token": "parties", "sentence_position": 5, "sentence_start": false, "sentence_end": false, "NEtag": "O"}, {"token": "will", "sentence_position": 6, "sentence_start": false, "sentence_end": false, "NEtag": "O"}, {"token": "soon", "sentence_position": 7, "sentence_start": false, "sentence_end": false, "NEtag": "O"}, {"token": "be", "sentence_position": 8, "sentence_start": false, "sentence_end": false, "NEtag": "O"}, {"token": "able", "sentence_position": 9, "sentence_start": false, "sentence_end": false, "NEtag": "O"}, {"token": "to", "sentence_position": 10, "sentence_start": false, "sentence_end": false, "NEtag": "O"}, {"token": "embark", "sentence_position": 11, "sentence_start": false, "sentence_end": false, "NEtag": "O"}, {"token": "on", "sentence_position": 12, "sentence_start": false, "sentence_end": false, "NEtag": "O"}, {"token": "negotiations", "sentence_position": 13, "sentence_start": false, "sentence_end": false, "NEtag": "O"}, {"token": "towards", "sentence_position": 14, "sentence_start": false, "sentence_end": false, "NEtag": "O"}, {"token": "an", "sentence_position": 15, "sentence_start": false, "sentence_end": false, "NEtag": "O"}, {"token": "interim", "sentence_position": 16, "sentence_start": false, "sentence_end": false, "NEtag": "O"}, {"token": "administration", "sentence_position": 17, "sentence_start": false, "sentence_end": false, "NEtag": "O"}, {"token": "for", "sentence_position": 18, "sentence_start": false, "sentence_end": false, "NEtag": "O"}, {"token": "the", "sentence_position": 19, "sentence_start": false, "sentence_end": false, "NEtag": "O"}, {"token": "North-East", "sentence_position": 20, "sentence_start": false, "sentence_end": false, "NEtag": "I-LOC"}, {"token": "Province", "sentence_position": 21, "sentence_start": false, "sentence_end": false, "NEtag": "I-LOC"}, {"token": ".", "sentence_position": 22, "sentence_start": false, "sentence_end": true, "NEtag": "O"}], "chunk_tags": [["PPSS", "B-NP"], ["BER", "O"], ["JJ", "I-NP"], ["CS", "O"], ["AT", "B-NP"], ["NNS", "I-NP"], ["MD", "O"], ["RB", "O"], ["BE", "O"], ["JJ", "I-NP"], ["TO", "O"], ["VB", "O"], ["IN", "O"], ["NNS", "I-NP"], ["IN", "O"], ["AT", "B-NP"], ["NN", "I-NP"], ["NN", "I-NP"], ["IN", "O"], ["AT", "B-NP"], ["``", "I-NP"], ["NN-TL", "I-NP"], [".", "O"]], "sentence_POS": [["We", "PPSS"], ["are", "BER"], ["hopeful", "JJ"], ["that", "CS"], ["the", "AT"], ["parties", "NNS"], ["will", "MD"], ["soon", "RB"], ["be", "BE"], ["able", "JJ"], ["to", "TO"], ["embark", "VB"], ["on", "IN"], ["negotiations", "NNS"], ["towards", "IN"], ["an", "AT"], ["interim", "NN"], ["administration", "NN"], ["for", "IN"], ["the", "AT"], ["North-East", "``"], ["Province", "NN-TL"], [".", "."]]}