{"sentence_LOW": ["That", "is", "especially", "true", "in", "the", "case", "of", "Zimbabwe", "."], "sentence_words": [{"token": "That", "sentence_position": 0, "sentence_start": true, "sentence_end": false, "NEtag": "O"}, {"token": "is", "sentence_position": 1, "sentence_start": false, "sentence_end": false, "NEtag": "O"}, {"token": "especially", "sentence_position": 2, "sentence_start": false, "sentence_end": false, "NEtag": "O"}, {"token": "true", "sentence_position": 3, "sentence_start": false, "sentence_end": false, "NEtag": "O"}, {"token": "in", "sentence_position": 4, "sentence_start": false, "sentence_end": false, "NEtag": "O"}, {"token": "the", "sentence_position": 5, "sentence_start": false, "sentence_end": false, "NEtag": "O"}, {"token": "case", "sentence_position": 6, "sentence_start": false, "sentence_end": false, "NEtag": "O"}, {"token": "of", "sentence_position": 7, "sentence_start": false, "sentence_end": false, "NEtag": "O"}, {"token": "Zimbabwe", "sentence_position": 8, "sentence_start": false, "sentence_end": false, "NEtag": "I-LOC"}, {"token": ".", "sentence_position": 9, "sentence_start": false, "sentence_end": true, "NEtag": "O"}], "chunk_tags": [["DT", "B-NP"], ["BEZ", "O"], ["QL", "O"], ["JJ", "I-NP"], ["IN", "O"], ["AT", "B-NP"], ["NN", "I-NP"], ["IN", "O"], ["``", "I-NP"], [".", "O"]], "sentence_POS": [["That", "DT"], ["is", "BEZ"], ["especially", "QL"], ["true", "JJ"], ["in", "IN"], ["the", "AT"], ["case", "NN"], ["of", "IN"], ["Zimbabwe", "``"], [".", "."]]}