{"sentence_LOW": ["Combined", "with", "the", "exchange", "of", "views", "in", "the", "general", "debate", ",", "it", "will", "no", "doubt", "provide", "a", "useful", "backdrop", "to", "the", "meeting", "of", "the", "United", "Nations", "Framework", "Convention", "on", "Climate", "Change", "to", "be", "held", "later", "this", "year", "in", "Bali", ",", "Indonesia", "."], "sentence_words": [{"token": "Combined", "sentence_position": 0, "sentence_start": true, "sentence_end": false, "NEtag": "O"}, {"token": "with", "sentence_position": 1, "sentence_start": false, "sentence_end": false, "NEtag": "O"}, {"token": "the", "sentence_position": 2, "sentence_start": false, "sentence_end": false, "NEtag": "O"}, {"token": "exchange", "sentence_position": 3, "sentence_start": false, "sentence_end": false, "NEtag": "O"}, {"token": "of", "sentence_position": 4, "sentence_start": false, "sentence_end": false, "NEtag": "O"}, {"token": "views", "sentence_position": 5, "sentence_start": false, "sentence_end": false, "NEtag": "O"}, {"token": "in", "sentence_position": 6, "sentence_start": false, "sentence_end": false, "NEtag": "O"}, {"token": "the", "sentence_position": 7, "sentence_start": false, "sentence_end": false, "NEtag": "O"}, {"token": "general", "sentence_position": 8, "sentence_start": false, "sentence_end": false, "NEtag": "O"}, {"token": "debate", "sentence_position": 9, "sentence_start": false, "sentence_end": false, "NEtag": "O"}, {"token": ",", "sentence_position": 10, "sentence_start": false, "sentence_end": false, "NEtag": "O"}, {"token": "it", "sentence_position": 11, "sentence_start": false, "sentence_end": false, "NEtag": "O"}, {"token": "will", "sentence_position": 12, "sentence_start": false, "sentence_end": false, "NEtag": "O"}, {"token": "no", "sentence_position": 13, "sentence_start": false, "sentence_end": false, "NEtag": "O"}, {"token": "doubt", "sentence_position": 14, "sentence_start": false, "sentence_end": false, "NEtag": "O"}, {"token": "provide", "sentence_position": 15, "sentence_start": false, "sentence_end": false, "NEtag": "O"}, {"token": "a", "sentence_position": 16, "sentence_start": false, "sentence_end": false, "NEtag": "O"}, {"token": "useful", "sentence_position": 17, "sentence_start": false, "sentence_end": false, "NEtag": "O"}, {"token": "backdrop", "sentence_position": 18, "sentence_start": false, "sentence_end": false, "NEtag": "O"}, {"token": "to", "sentence_position": 19, "sentence_start": false, "sentence_end": false, "NEtag": "O"}, {"token": "the", "sentence_position": 20, "sentence_start": false, "sentence_end": false, "NEtag": "O"}, {"token": "meeting", "sentence_position": 21, "sentence_start": false, "sentence_end": false, "NEtag": "O"}, {"token": "of", "sentence_position": 22, "sentence_start": false, "sentence_end": false, "NEtag": "O"}, {"token": "the", "sentence_position": 23, "sentence_start": false, "sentence_end": false, "NEtag": "O"}, {"token": "United", "sentence_position": 24, "sentence_start": false, "sentence_end": false, "NEtag": "I-ORG"}, {"token": "Nations", "sentence_position": 25, "sentence_start": false, "sentence_end": false, "NEtag": "I-ORG"}, {"token": "Framework", "sentence_position": 26, "sentence_start": false, "sentence_end": false, "NEtag": "I-MISC"}, {"token": "Convention", "sentence_position": 27, "sentence_start": false, "sentence_end": false, "NEtag": "I-MISC"}, {"token": "on", "sentence_position": 28, "sentence_start": false, "sentence_end": false, "NEtag": "I-MISC"}, {"token": "Climate", "sentence_position": 29, "sentence_start": false, "sentence_end": false, "NEtag": "I-MISC"}, {"token": "Change", "sentence_position": 30, "sentence_start": false, "sentence_end": false, "NEtag": "I-MISC"}, {"token": "to", "sentence_position": 31, "sentence_start": false, "sentence_end": false, "NEtag": "O"}, {"token": "be", "sentence_position": 32, "sentence_start": false, "sentence_end": false, "NEtag": "O"}, {"token": "held", "sentence_position": 33, "sentence_start": false, "sentence_end": false, "NEtag": "O"}, {"token": "later", "sentence_position": 34, "sentence_start": false, "sentence_end": false, "NEtag": "O"}, {"token": "this", "sentence_position": 35, "sentence_start": false, "sentence_end": false, "NEtag": "O"}, {"token": "year", "sentence_position": 36, "sentence_start": false, "sentence_end": false, "NEtag": "O"}, {"token": "in", "sentence_position": 37, "sentence_start": false, "sentence_end": false, "NEtag": "O"}, {"token": "Bali", "sentence_position": 38, "sentence_start": false, "sentence_end": false, "NEtag": "I-LOC"}, {"token": ",", "sentence_position": 39, "sentence_start": false, "sentence_end": false, "NEtag": "O"}, {"token": "Indonesia", "sentence_position": 40, "sentence_start": false, "sentence_end": false, "NEtag": "I-LOC"}, {"token": ".", "sentence_position": 41, "sentence_start": false, "sentence_end": true, "NEtag": "O"}], "sentence_POS": [["Combined", "VBN-TL"], ["with", "IN"], ["the", "AT"], ["exchange", "NN"], ["of", "IN"], ["views", "NNS"], ["in", "IN"], ["the", "AT"], ["general", "JJ"], ["debate", "NN"], [",", ","], ["it", "PPS"], ["will", "MD"], ["no", "AT"], ["doubt", "NN"], ["provide", "VB"], ["a", "AT"], ["useful", "JJ"], ["backdrop", "NN"], ["to", "IN"], ["the", "AT"], ["meeting", "NN"], ["of", "IN"], ["the", "AT"], ["United", "VBN-TL"], ["Nations", "NNS-TL"], ["Framework", "``"], ["Convention", "NN-TL"], ["on", "IN"], ["Climate", "``"], ["Change", "NN-HL"], ["to", "IN-HL"], ["be", "BE"], ["held", "VBN"], ["later", "RBR"], ["this", "DT"], ["year", "NN"], ["in", "IN"], ["Bali", "NP"], [",", ","], ["Indonesia", "NP"], [".", "."]]}