{"sentence_LOW": ["New", "Zealand", "played", "an", "active", "part", "in", "the", "design", "of", "the", "new", "Human", "Rights", "Council", ",", "and", "we", "are", "seeking", "election", "to", "the", "Council", "next", "year", ",", "so", "as", "to", "be", "more", "closely", "involved", "in", "its", "work", "."], "sentence_words": [{"token": "New", "sentence_position": 0, "sentence_start": true, "sentence_end": false, "NEtag": "I-LOC"}, {"token": "Zealand", "sentence_position": 1, "sentence_start": false, "sentence_end": false, "NEtag": "I-LOC"}, {"token": "played", "sentence_position": 2, "sentence_start": false, "sentence_end": false, "NEtag": "O"}, {"token": "an", "sentence_position": 3, "sentence_start": false, "sentence_end": false, "NEtag": "O"}, {"token": "active", "sentence_position": 4, "sentence_start": false, "sentence_end": false, "NEtag": "O"}, {"token": "part", "sentence_position": 5, "sentence_start": false, "sentence_end": false, "NEtag": "O"}, {"token": "in", "sentence_position": 6, "sentence_start": false, "sentence_end": false, "NEtag": "O"}, {"token": "the", "sentence_position": 7, "sentence_start": false, "sentence_end": false, "NEtag": "O"}, {"token": "design", "sentence_position": 8, "sentence_start": false, "sentence_end": false, "NEtag": "O"}, {"token": "of", "sentence_position": 9, "sentence_start": false, "sentence_end": false, "NEtag": "O"}, {"token": "the", "sentence_position": 10, "sentence_start": false, "sentence_end": false, "NEtag": "O"}, {"token": "new", "sentence_position": 11, "sentence_start": false, "sentence_end": false, "NEtag": "O"}, {"token": "Human", "sentence_position": 12, "sentence_start": false, "sentence_end": false, "NEtag": "I-ORG"}, {"token": "Rights", "sentence_position": 13, "sentence_start": false, "sentence_end": false, "NEtag": "I-ORG"}, {"token": "Council", "sentence_position": 14, "sentence_start": false, "sentence_end": false, "NEtag": "I-ORG"}, {"token": ",", "sentence_position": 15, "sentence_start": false, "sentence_end": false, "NEtag": "O"}, {"token": "and", "sentence_position": 16, "sentence_start": false, "sentence_end": false, "NEtag": "O"}, {"token": "we", "sentence_position": 17, "sentence_start": false, "sentence_end": false, "NEtag": "O"}, {"token": "are", "sentence_position": 18, "sentence_start": false, "sentence_end": false, "NEtag": "O"}, {"token": "seeking", "sentence_position": 19, "sentence_start": false, "sentence_end": false, "NEtag": "O"}, {"token": "election", "sentence_position": 20, "sentence_start": false, "sentence_end": false, "NEtag": "O"}, {"token": "to", "sentence_position": 21, "sentence_start": false, "sentence_end": false, "NEtag": "O"}, {"token": "the", "sentence_position": 22, "sentence_start": false, "sentence_end": false, "NEtag": "O"}, {"token": "Council", "sentence_position": 23, "sentence_start": false, "sentence_end": false, "NEtag": "I-ORG"}, {"token": "next", "sentence_position": 24, "sentence_start": false, "sentence_end": false, "NEtag": "O"}, {"token": "year", "sentence_position": 25, "sentence_start": false, "sentence_end": false, "NEtag": "O"}, {"token": ",", "sentence_position": 26, "sentence_start": false, "sentence_end": false, "NEtag": "O"}, {"token": "so", "sentence_position": 27, "sentence_start": false, "sentence_end": false, "NEtag": "O"}, {"token": "as", "sentence_position": 28, "sentence_start": false, "sentence_end": false, "NEtag": "O"}, {"token": "to", "sentence_position": 29, "sentence_start": false, "sentence_end": false, "NEtag": "O"}, {"token": "be", "sentence_position": 30, "sentence_start": false, "sentence_end": false, "NEtag": "O"}, {"token": "more", "sentence_position": 31, "sentence_start": false, "sentence_end": false, "NEtag": "O"}, {"token": "closely", "sentence_position": 32, "sentence_start": false, "sentence_end": false, "NEtag": "O"}, {"token": "involved", "sentence_position": 33, "sentence_start": false, "sentence_end": false, "NEtag": "O"}, {"token": "in", "sentence_position": 34, "sentence_start": false, "sentence_end": false, "NEtag": "O"}, {"token": "its", "sentence_position": 35, "sentence_start": false, "sentence_end": false, "NEtag": "O"}, {"token": "work", "sentence_position": 36, "sentence_start": false, "sentence_end": false, "NEtag": "O"}, {"token": ".", "sentence_position": 37, "sentence_start": false, "sentence_end": true, "NEtag": "O"}], "sentence_POS": [["New", "JJ-TL"], ["Zealand", "NP-TL"], ["played", "VBD"], ["an", "AT"], ["active", "JJ"], ["part", "NN"], ["in", "IN"], ["the", "AT"], ["design", "NN"], ["of", "IN"], ["the", "AT"], ["new", "JJ"], ["Human", "JJ-TL"], ["Rights", "NNS-TL"], ["Council", "NN-TL"], [",", ","], ["and", "CC"], ["we", "PPSS"], ["are", "BER"], ["seeking", "VBG"], ["election", "NN"], ["to", "IN"], ["the", "AT"], ["Council", "NN-TL"], ["next", "AP"], ["year", "NN"], [",", ","], ["so", "CS"], ["as", "CS"], ["to", "TO"], ["be", "BE"], ["more", "QL"], ["closely", "RB"], ["involved", "VBN"], ["in", "IN"], ["its", "PP$"], ["work", "NN"], [".", "."]]}