[{"token": "\ufffcThe", "sentence_position": 0, "sentence_start": true, "sentence_end": false, "NEtag": "O", "case": "upper", "last_char": "e", "geoText_loc": false, "known_org": false, "known_prog": false, "hyphen": false, "prev_token": null, "next_token": "United", "pos": "``", "chunktag": "I-NP", "prev_pos": null, "prev_chunktag": null, "next_pos": "VBN-TL-NC", "next_chunktag": "I-NP"}, {"token": "United", "sentence_position": 1, "sentence_start": false, "sentence_end": false, "NEtag": "I-ORG", "case": "upper", "last_char": "d", "geoText_loc": false, "known_org": true, "known_prog": false, "hyphen": false, "prev_token": "\ufffcThe", "next_token": "Nations", "pos": "VBN-TL-NC", "chunktag": "I-NP", "prev_pos": "``", "prev_chunktag": "I-NP", "next_pos": "NNS-TL", "next_chunktag": "I-NP"}, {"token": "Nations", "sentence_position": 2, "sentence_start": false, "sentence_end": false, "NEtag": "I-ORG", "case": "upper", "last_char": "s", "geoText_loc": false, "known_org": true, "known_prog": false, "hyphen": false, "prev_token": "United", "next_token": "is", "pos": "NNS-TL", "chunktag": "I-NP", "prev_pos": "VBN-TL-NC", "prev_chunktag": "I-NP", "next_pos": "BEZ", "next_chunktag": "O"}, {"token": "is", "sentence_position": 3, "sentence_start": false, "sentence_end": false, "NEtag": "O", "case": "lower", "last_char": "s", "geoText_loc": false, "known_org": false, "known_prog": false, "hyphen": false, "prev_token": "Nations", "next_token": "more", "pos": "BEZ", "chunktag": "O", "prev_pos": "NNS-TL", "prev_chunktag": "I-NP", "next_pos": "QL", "next_chunktag": "O"}, {"token": "more", "sentence_position": 4, "sentence_start": false, "sentence_end": false, "NEtag": "O", "case": "lower", "last_char": "e", "geoText_loc": false, "known_org": false, "known_prog": false, "hyphen": false, "prev_token": "is", "next_token": "necessary", "pos": "QL", "chunktag": "O", "prev_pos": "BEZ", "prev_chunktag": "O", "next_pos": "JJ", "next_chunktag": "I-NP"}, {"token": "necessary", "sentence_position": 5, "sentence_start": false, "sentence_end": false, "NEtag": "O", "case": "lower", "last_char": "y", "geoText_loc": false, "known_org": false, "known_prog": false, "hyphen": false, "prev_token": "more", "next_token": "than", "pos": "JJ", "chunktag": "I-NP", "prev_pos": "QL", "prev_chunktag": "O", "next_pos": "CS", "next_chunktag": "O"}, {"token": "than", "sentence_position": 6, "sentence_start": false, "sentence_end": false, "NEtag": "O", "case": "lower", "last_char": "n", "geoText_loc": false, "known_org": false, "known_prog": false, "hyphen": false, "prev_token": "necessary", "next_token": "ever", "pos": "CS", "chunktag": "O", "prev_pos": "JJ", "prev_chunktag": "I-NP", "next_pos": "RB", "next_chunktag": "O"}, {"token": "ever", "sentence_position": 7, "sentence_start": false, "sentence_end": false, "NEtag": "O", "case": "lower", "last_char": "r", "geoText_loc": false, "known_org": false, "known_prog": false, "hyphen": false, "prev_token": "than", "next_token": ".", "pos": "RB", "chunktag": "O", "prev_pos": "CS", "prev_chunktag": "O", "next_pos": ".", "next_chunktag": "O"}, {"token": ".", "sentence_position": 8, "sentence_start": false, "sentence_end": true, "NEtag": "O", "case": "lower", "last_char": ".", "geoText_loc": false, "known_org": false, "known_prog": false, "hyphen": false, "prev_token": "ever", "next_token": null, "pos": ".", "chunktag": "O", "prev_pos": "RB", "prev_chunktag": "O", "next_pos": null, "next_chunktag": null}]